chat_pdf/__init__.py
chat_pdf/chat_with_pdfs.py
chatting_with_pdfs-0.0.12.dist-info/LICENSE.txt
chatting_with_pdfs-0.0.12.dist-info/METADATA
chatting_with_pdfs-0.0.12.dist-info/WHEEL
chatting_with_pdfs-0.0.12.dist-info/top_level.txt
chatting_with_pdfs-0.0.12.dist-info/RECORD
