Metadata-Version: 2.1
Name: chatting-with-pdfs
Version: 0.0.12
Summary: Load a PDF file and ask questions via llama_index and GPT.
Author: Morne
License: MIT
Classifier: License :: OSI Approved :: MIT License
Classifier: Programming Language :: Python :: 3.10
Classifier: Operating System :: OS Independent
Requires-Python: >=3.10
License-File: LICENSE.txt
Requires-Dist: bson (>=0.5.10)
Requires-Dist: openai (>=0.27.6)
Requires-Dist: langchain (>=0.0.160)
Requires-Dist: setuptools (>=67.8.0)
Requires-Dist: llama-index (>=0.6.7)
Requires-Dist: PyPDF2 (>=3.0.1)
Provides-Extra: dev
Requires-Dist: pytest (>=7.4.0) ; extra == 'dev'
Requires-Dist: twine (>=4.0.2) ; extra == 'dev'
